SOARegression/__init__.py
SOARegression/model.py
SOARegression/transformer.py
SOARegression-0.0.3.dist-info/LICENSE.txt
SOARegression-0.0.3.dist-info/METADATA
SOARegression-0.0.3.dist-info/WHEEL
SOARegression-0.0.3.dist-info/top_level.txt
SOARegression-0.0.3.dist-info/RECORD
